{
    "airspace": [
        {
            "id": "South",
            "group": "CTR",
            "owner": [
                "BBE",
                "BB2",
                "BB1",
                "fss/GULFE",
                "fss/GULF"
            ],
            "sectors": [
                {
                    "min": 245,
                    "max": 344,
                    "points": [
                        ["244508","0514402"],
                        ["244900","0520000"],
                        ["245046","0522215"],
                        ["244749","0522003"],
                        ["240300","0514700"],
                        ["235816","0514308"],
                        ["240724","0513526"],
                        ["241458","0513526"],
                        ["242536","0513459"],
                        ["243036","0513448"],
                        ["244056","0513426"],
                        ["244247","0513422"],
                        ["244508","0514402"]
                    ]
                }
            ]
        },
        {
            "id": "South",
            "group": "CTR",
            "owner": [
                "BBE",
                "BB2",
                "BB1"
            ],
            "sectors": [
                {
                    "min": 45,
                    "max": 244,
                    "points": [
                        ["244508","0514402"],
                        ["244900","0520000"],
                        ["245046","0522215"],
                        ["244749","0522003"],
                        ["240300","0514700"],
                        ["235816","0514308"],
                        ["240724","0513526"],
                        ["241458","0513526"],
                        ["242536","0513459"],
                        ["243036","0513448"],
                        ["244056","0513426"],
                        ["244247","0513422"],
                        ["244508","0514402"]
                    ]
                }
            ]
        },
        {
            "id": "South (High)",
            "group": "CTR",
            "owner": [
                "BBE",
                "BB2",
                "BB1",
                "fss/GULFE",
                "fss/GULF"
            ],
            "sectors": [
                {
                    "min": 345,
                    "max": 659,
                    "points": [
                        ["244508","0514402"],
                        ["244900","0520000"],
                        ["245046","0522215"],
                        ["244749","0522003"],
                        ["240300","0514700"],
                        ["235816","0514308"],
                        ["240724","0513526"],
                        ["241458","0513526"],
                        ["242536","0513459"],
                        ["243036","0513448"],
                        ["244056","0513426"],
                        ["244247","0513422"],
                        ["244508","0514402"]
                    ]
                }
            ]
        },
        {
            "id": "North",
            "group": "CTR",
            "owner": [
                "BBN",
                "BB3",
                "BB1",
                "fss/GULFE",
                "fss/GULF"
            ],
            "sectors": [
                {
                    "min": 245,
                    "max": 344,
                    "points": [
                        ["280358","0485905"],
                        ["275000","0490800"],
                        ["272811","0493027"],
                        ["271840","0494014"],
                        ["270838","0495202"],
                        ["270757","0503655"],
                        ["271557","0504650"],
                        ["280300","0501041"],
                        ["284400","0494000"],
                        ["283353","0492316"],
                        ["282718","0491222"],
                        ["281500","0485200"],
                        ["280358","0485905"]
                    ]
                }
            ]
        },
        {
            "id": "North",
            "group": "CTR",
            "owner": [
                "BBN",
                "BB3",
                "BB1"
            ],
            "sectors": [
                {
                    "min": 0,
                    "max": 344,
                    "points": [
                        ["280358","0485905"],
                        ["275000","0490800"],
                        ["272811","0493027"],
                        ["271840","0494014"],
                        ["270838","0495202"],
                        ["270757","0503655"],
                        ["271557","0504650"],
                        ["280300","0501041"],
                        ["284400","0494000"],
                        ["283353","0492316"],
                        ["282718","0491222"],
                        ["281500","0485200"],
                        ["280358","0485905"]
                    ]
                }
            ]
        },
        {
            "id": "North (High)",
            "group": "CTR",
            "owner": [
                "BB3",
                "BB1",
                "fss/GULFE",
                "fss/GULF"
            ],
            "sectors": [
                {
                    "min": 345,
                    "max": 659,
                    "points": [
                        ["280358","0485905"],
                        ["275000","0490800"],
                        ["272811","0493027"],
                        ["271840","0494014"],
                        ["270838","0495202"],
                        ["270757","0503655"],
                        ["271557","0504650"],
                        ["280300","0501041"],
                        ["284400","0494000"],
                        ["283353","0492316"],
                        ["282718","0491222"],
                        ["281500","0485200"],
                        ["280358","0485905"]
                    ]
                }
            ]
        },
        {
            "id": "East",
            "group": "CTR",
            "owner": [
                "BBE",
                "BB2",
                "BB1",
                "fss/GULFE",
                "fss/GULF"
            ],
            "sectors": [
                {
                    "min": 245,
                    "max": 344,
                    "points": [
                        ["264440","0514359"],
                        ["262622","0524357"],
                        ["261200","0533045"],
                        ["260532","0530457"],
                        ["260256","0530406"],
                        ["255442","0532522"],
                        ["255211","0531651"],
                        ["254900","0530600"],
                        ["253815","0525751"],
                        ["261356","0513849"],
                        ["264440","0514359"]
                    ]
                }
            ]
        },
        {
            "id": "East (High)",
            "group": "CTR",
            "owner": [
                "BB2",
                "BB1",
                "fss/GULFE",
                "fss/GULF"
            ],
            "sectors": [
                {
                    "min": 345,
                    "max": 659,
                    "points": [
                        ["264440","0514359"],
                        ["262622","0524357"],
                        ["261200","0533045"],
                        ["260532","0530457"],
                        ["260256","0530406"],
                        ["255442","0532522"],
                        ["255211","0531651"],
                        ["254900","0530600"],
                        ["253815","0525751"],
                        ["261356","0513849"],
                        ["264440","0514359"]
                    ]
                }
            ]
        },
        {
            "id": "Central (High)",
            "group": "CTR",
            "owner": [
                "BB1",
                "fss/GULFE",
                "fss/GULF"
            ],
            "sectors": [
                {
                    "min": 345,
                    "max": 659,
                    "points": [
                        ["265644","0500434"],
                        ["265234","0500855"],
                        ["263420","0502759"],
                        ["263148","0502315"],
                        ["262424","0502218"],
                        ["262217","0502026"],
                        ["261515","0501907"],
                        ["261018","0501852"],
                        ["260450","0501611"],
                        ["255709","0501735"],
                        ["255301","0501807"],
                        ["254908","0502201"],
                        ["254227","0502503"],
                        ["254115","0502606"],
                        ["253540","0503151"],
                        ["253400","0503319"],
                        ["253434","0503403"],
                        ["253510","0503448"],
                        ["253453","0504122"],
                        ["253450","0504135"],
                        ["253421","0504405"],
                        ["253329","0504549"],
                        ["253249","0504611"],
                        ["253255","0504648"],
                        ["253243","0504746"],
                        ["253206","0504836"],
                        ["253240","0504854"],
                        ["253255","0504848"],
                        ["253344","0504904"],
                        ["253349","0504832"],
                        ["253433","0504737"],
                        ["253533","0504649"],
                        ["253721","0504754"],
                        ["253745","0504944"],
                        ["253819","0505022"],
                        ["253843","0505026"],
                        ["253931","0505006"],
                        ["254010","0505030"],
                        ["254127","0505143"],
                        ["254227","0505109"],
                        ["254407","0505158"],
                        ["254458","0505205"],
                        ["254535","0505153"],
                        ["254600","0505140"],
                        ["254657","0505123"],
                        ["254843","0505032"],
                        ["255140","0504953"],
                        ["255226","0504912"],
                        ["255342","0504857"],
                        ["260040","0505100"],
                        ["260438","0505427"],
                        ["261102","0505503"],
                        ["261330","0505513"],
                        ["261609","0510016"],
                        ["261818","0510158"],
                        ["262117","0510420"],
                        ["262340","0511220"],
                        ["262134","0512301"],
                        ["261356","0513849"],
                        ["264440","0514359"],
                        ["265455","0511017"],
                        ["265500","0511000"],
                        ["265810","0510515"],
                        ["270500","0505500"],
                        ["271557","0504650"],
                        ["270757","0503655"],
                        ["270838","0495202"],
                        ["265644","0500434"]
                    ]
                }
            ]
        },
        {
            "id": "Central",
            "group": "CTR",
            "owner": [
                "BBCH",
                "BB1",
                "fss/GULFE",
                "fss/GULF"
            ],
            "sectors": [
                {
                    "min": 295,
                    "max": 344,
                    "points": [
                        ["265644","0500434"],
                        ["265234","0500855"],
                        ["263420","0502759"],
                        ["263148","0502315"],
                        ["262424","0502218"],
                        ["262217","0502026"],
                        ["261515","0501907"],
                        ["261018","0501852"],
                        ["260450","0501611"],
                        ["255709","0501735"],
                        ["255301","0501807"],
                        ["254908","0502201"],
                        ["254227","0502503"],
                        ["254115","0502606"],
                        ["253540","0503151"],
                        ["253400","0503319"],
                        ["253434","0503403"],
                        ["253510","0503448"],
                        ["253453","0504122"],
                        ["253450","0504135"],
                        ["253421","0504405"],
                        ["253329","0504549"],
                        ["253249","0504611"],
                        ["253255","0504648"],
                        ["253243","0504746"],
                        ["253206","0504836"],
                        ["253240","0504854"],
                        ["253255","0504848"],
                        ["253344","0504904"],
                        ["253349","0504832"],
                        ["253433","0504737"],
                        ["253533","0504649"],
                        ["253721","0504754"],
                        ["253745","0504944"],
                        ["253819","0505022"],
                        ["253843","0505026"],
                        ["253931","0505006"],
                        ["254010","0505030"],
                        ["254127","0505143"],
                        ["254227","0505109"],
                        ["254407","0505158"],
                        ["254458","0505205"],
                        ["254535","0505153"],
                        ["254600","0505140"],
                        ["254657","0505123"],
                        ["254843","0505032"],
                        ["255140","0504953"],
                        ["255226","0504912"],
                        ["255342","0504857"],
                        ["260040","0505100"],
                        ["260438","0505427"],
                        ["261102","0505503"],
                        ["261330","0505513"],
                        ["261609","0510016"],
                        ["261818","0510158"],
                        ["262117","0510420"],
                        ["262340","0511220"],
                        ["262134","0512301"],
                        ["261356","0513849"],
                        ["264440","0514359"],
                        ["265455","0511017"],
                        ["265500","0511000"],
                        ["265810","0510515"],
                        ["270500","0505500"],
                        ["271557","0504650"],
                        ["270757","0503655"],
                        ["270838","0495202"],
                        ["265644","0500434"]
                    ]
                },
                {
                    "min": 245,
                    "max": 294,
                    "points": [
                        ["253400","0503319"],
                        ["253434","0503403"],
                        ["253510","0503448"],
                        ["253453","0504122"],
                        ["253450","0504135"],
                        ["253421","0504405"],
                        ["253329","0504549"],
                        ["253249","0504611"],
                        ["253255","0504648"],
                        ["253243","0504746"],
                        ["253206","0504836"],
                        ["253240","0504854"],
                        ["253255","0504848"],
                        ["253344","0504904"],
                        ["253349","0504832"],
                        ["253433","0504737"],
                        ["253533","0504649"],
                        ["253721","0504754"],
                        ["253745","0504944"],
                        ["253819","0505022"],
                        ["253843","0505026"],
                        ["253931","0505006"],
                        ["254010","0505030"],
                        ["254127","0505143"],
                        ["254227","0505109"],
                        ["254407","0505158"],
                        ["254458","0505205"],
                        ["254535","0505153"],
                        ["254600","0505140"],
                        ["254657","0505123"],
                        ["254843","0505032"],
                        ["255140","0504953"],
                        ["255226","0504912"],
                        ["255342","0504857"],
                        ["260040","0505100"],
                        ["260438","0505427"],
                        ["261102","0505503"],
                        ["261330","0505513"],
                        ["261609","0510016"],
                        ["261818","0510158"],
                        ["262117","0510420"],
                        ["262340","0511220"],
                        ["262134","0512301"],
                        ["261356","0513849"],
                        ["264440","0514359"],
                        ["265455","0511017"],
                        ["265500","0511000"],
                        ["265810","0510515"],
                        ["270500","0505500"],
                        ["271557","0504650"],
                        ["270757","0503655"],
                        ["270838","0495202"],
                        ["265644","0500434"],
                        ["265234","0500855"],
                        ["263420","0502759"],
                        ["263148","0502315"],
                        ["262424","0502218"],
                        ["262217","0502026"],
                        ["261515","0501907"],
                        ["261018","0501852"],
                        ["260450","0501611"],
                        ["255709","0501735"],
                        ["255301","0501807"],
                        ["254908","0502201"],
                        ["254227","0502503"],
                        ["254115","0502606"],
                        ["253540","0503151"],
                        ["253400","0503319"]
                    ]
                }
            ]
        },
        {
            "id": "Central",
            "group": "CTR",
            "owner": [
                "BBCL",
                "BBCH",
                "BB1"
            ],
            "sectors": [
                {
                    "min": 170,
                    "max": 294,
                    "points": [
                        ["253400","0503319"],
                        ["253434","0503403"],
                        ["253510","0503448"],
                        ["253453","0504122"],
                        ["253450","0504135"],
                        ["253421","0504405"],
                        ["253329","0504549"],
                        ["253249","0504611"],
                        ["253255","0504648"],
                        ["253243","0504746"],
                        ["253206","0504836"],
                        ["253240","0504854"],
                        ["253255","0504848"],
                        ["253344","0504904"],
                        ["253349","0504832"],
                        ["253433","0504737"],
                        ["253533","0504649"],
                        ["253721","0504754"],
                        ["253745","0504944"],
                        ["253819","0505022"],
                        ["253843","0505026"],
                        ["253931","0505006"],
                        ["254010","0505030"],
                        ["254127","0505143"],
                        ["254227","0505109"],
                        ["254407","0505158"],
                        ["254458","0505205"],
                        ["254535","0505153"],
                        ["254600","0505140"],
                        ["254657","0505123"],
                        ["254843","0505032"],
                        ["255140","0504953"],
                        ["255226","0504912"],
                        ["255342","0504857"],
                        ["260040","0505100"],
                        ["260438","0505427"],
                        ["261102","0505503"],
                        ["261330","0505513"],
                        ["261609","0510016"],
                        ["261818","0510158"],
                        ["262117","0510420"],
                        ["262340","0511220"],
                        ["262134","0512301"],
                        ["261356","0513849"],
                        ["264440","0514359"],
                        ["265455","0511017"],
                        ["265500","0511000"],
                        ["265810","0510515"],
                        ["270500","0505500"],
                        ["271557","0504650"],
                        ["270757","0503655"],
                        ["270838","0495202"],
                        ["265644","0500434"],
                        ["265234","0500855"],
                        ["263420","0502759"],
                        ["263148","0502315"],
                        ["262424","0502218"],
                        ["262217","0502026"],
                        ["261515","0501907"],
                        ["261018","0501852"],
                        ["260450","0501611"],
                        ["255709","0501735"],
                        ["255301","0501807"],
                        ["254908","0502201"],
                        ["254227","0502503"],
                        ["254115","0502606"],
                        ["253540","0503151"],
                        ["253400","0503319"]
                    ]
                },
                {
                    "min": 45,
                    "max": 169,
                    "points": [
                        ["271557","0504650"],
                        ["270500","0505500"],
                        ["265810","0510515"],
                        ["265500","0511000"],
                        ["265455","0511017"],
                        ["264440","0514359"],
                        ["261356","0513849"],
                        ["262134","0512301"],
                        ["262744","0512142"],
                        ["263333","0511902"],
                        ["263855","0511522"],
                        ["264342","0511050"],
                        ["264747","0510531"],
                        ["265105","0505933"],
                        ["265330","0505305"],
                        ["265458","0504617"],
                        ["265553","0504134"],
                        ["265644","0500434"],
                        ["270838","0495202"],
                        ["270757","0503655"],
                        ["271557","0504650"]
                    ]
                }
            ]
        },
        {
            "id": "Bahrain",
            "group": "APP",
            "owner": [
                "BA",
                "BBCL",
                "BBCH",
                "BB1"
            ],
            "sectors": [
                {
                    "min": 25,
                    "max": 79,
                    "points": [
                        ["261018","0501852"],
                        ["260412","0503022"],
                        ["260412","0503022"],
                        ["260322","0502853"],
                        ["260322","0502853"],
                        ["260300","0502817"],
                        ["260300","0502817"],
                        ["260221","0502733"],
                        ["260221","0502733"],
                        ["260110","0502625"],
                        ["260110","0502625"],
                        ["255949","0502530"],
                        ["255949","0502530"],
                        ["255823","0502451"],
                        ["255823","0502451"],
                        ["255651","0502426"],
                        ["255651","0502426"],
                        ["255517","0502418"],
                        ["255517","0502418"],
                        ["255343","0502426"],
                        ["255343","0502426"],
                        ["255212","0502451"],
                        ["255212","0502451"],
                        ["255051","0502155"],
                        ["255051","0502155"],
                        ["254924","0502234"],
                        ["254924","0502234"],
                        ["254740","0502345"],
                        ["254740","0502345"],
                        ["254607","0502513"],
                        ["254607","0502513"],
                        ["254448","0502657"],
                        ["254448","0502657"],
                        ["254345","0502852"],
                        ["254345","0502852"],
                        ["254258","0503058"],
                        ["254258","0503058"],
                        ["254229","0503310"],
                        ["254229","0503310"],
                        ["254220","0503525"],
                        ["254220","0503525"],
                        ["254229","0503741"],
                        ["254229","0503741"],
                        ["254258","0503953"],
                        ["254258","0503953"],
                        ["254345","0504158"],
                        ["254345","0504158"],
                        ["254448","0504354"],
                        ["254448","0504354"],
                        ["254607","0504537"],
                        ["254607","0504537"],
                        ["254740","0504705"],
                        ["254740","0504705"],
                        ["254924","0504816"],
                        ["254924","0504816"],
                        ["254458","0505205"],
                        ["254458","0505205"],
                        ["254227","0505109"],
                        ["254227","0505109"],
                        ["253643","0504847"],
                        ["253643","0504847"],
                        ["253433","0504737"],
                        ["253433","0504737"],
                        ["253255","0504648"],
                        ["253255","0504648"],
                        ["252849","0504455"],
                        ["252849","0504455"],
                        ["251522","0503848"],
                        ["251522","0503848"],
                        ["251849","0503855"],
                        ["251849","0503855"],
                        ["252144","0503818"],
                        ["252144","0503818"],
                        ["252336","0503741"],
                        ["252336","0503741"],
                        ["252510","0503716"],
                        ["252510","0503716"],
                        ["252828","0503653"],
                        ["252828","0503653"],
                        ["253111","0503544"],
                        ["253111","0503544"],
                        ["253400","0503319"],
                        ["253400","0503319"],
                        ["253540","0503151"],
                        ["253540","0503151"],
                        ["254115","0502606"],
                        ["254115","0502606"],
                        ["254227","0502503"],
                        ["254227","0502503"],
                        ["254908","0502201"],
                        ["254908","0502201"],
                        ["255301","0501807"],
                        ["255301","0501807"],
                        ["255709","0501735"],
                        ["255709","0501735"],
                        ["260450","0501611"],
                        ["260450","0501611"],
                        ["261018","0501852"]
                    ]
                },
                {
                    "min": 10,
                    "max": 24,
                    "points": [
                        ["263420","0502759"],
                        ["260816","0503525"],
                        ["260816","0503525"],
                        ["260517","0503525"],
                        ["260517","0503525"],
                        ["260510","0503340"],
                        ["260510","0503340"],
                        ["260508","0503323"],
                        ["260508","0503323"],
                        ["260456","0503229"],
                        ["260456","0503229"],
                        ["260448","0503158"],
                        ["260448","0503158"],
                        ["260412","0503023"],
                        ["260412","0503023"],
                        ["260323","0502853"],
                        ["260323","0502853"],
                        ["260300","0502817"],
                        ["260300","0502817"],
                        ["260221","0502733"],
                        ["260221","0502733"],
                        ["260110","0502625"],
                        ["260110","0502625"],
                        ["255949","0502530"],
                        ["255949","0502530"],
                        ["255822","0502450"],
                        ["255822","0502450"],
                        ["255651","0502426"],
                        ["255651","0502426"],
                        ["255517","0502418"],
                        ["255517","0502418"],
                        ["255343","0502426"],
                        ["255343","0502426"],
                        ["255212","0502451"],
                        ["255212","0502451"],
                        ["255051","0502155"],
                        ["255051","0502155"],
                        ["254924","0502234"],
                        ["254924","0502234"],
                        ["254740","0502345"],
                        ["254740","0502345"],
                        ["254607","0502513"],
                        ["254607","0502513"],
                        ["254448","0502657"],
                        ["254448","0502657"],
                        ["254345","0502852"],
                        ["254345","0502852"],
                        ["254258","0503058"],
                        ["254258","0503058"],
                        ["254229","0503310"],
                        ["254229","0503310"],
                        ["254220","0503525"],
                        ["254220","0503525"],
                        ["254229","0503741"],
                        ["254229","0503741"],
                        ["254258","0503953"],
                        ["254258","0503953"],
                        ["254345","0504158"],
                        ["254345","0504158"],
                        ["254448","0504354"],
                        ["254448","0504354"],
                        ["254607","0504537"],
                        ["254607","0504537"],
                        ["254740","0504705"],
                        ["254740","0504705"],
                        ["254924","0504816"],
                        ["254924","0504816"],
                        ["255117","0504908"],
                        ["255117","0504908"],
                        ["255316","0504940"],
                        ["255316","0504940"],
                        ["255517","0504951"],
                        ["255517","0504951"],
                        ["255719","0504940"],
                        ["255719","0504940"],
                        ["255918","0504908"],
                        ["255918","0504908"],
                        ["260111","0504816"],
                        ["260111","0504816"],
                        ["260255","0504705"],
                        ["260255","0504705"],
                        ["260428","0504537"],
                        ["260428","0504537"],
                        ["260547","0504354"],
                        ["260547","0504354"],
                        ["261706","0510440"],
                        ["261706","0510440"],
                        ["254458","0505205"],
                        ["254458","0505205"],
                        ["254227","0505109"],
                        ["254227","0505109"],
                        ["253643","0504847"],
                        ["253643","0504847"],
                        ["253433","0504737"],
                        ["253433","0504737"],
                        ["253255","0504648"],
                        ["253255","0504648"],
                        ["252849","0504455"],
                        ["252849","0504455"],
                        ["251522","0503848"],
                        ["251522","0503848"],
                        ["251849","0503855"],
                        ["251849","0503855"],
                        ["252144","0503818"],
                        ["252144","0503818"],
                        ["252336","0503741"],
                        ["252336","0503741"],
                        ["252510","0503716"],
                        ["252510","0503716"],
                        ["252828","0503653"],
                        ["252828","0503653"],
                        ["253111","0503544"],
                        ["253111","0503544"],
                        ["253400","0503319"],
                        ["253400","0503319"],
                        ["253540","0503151"],
                        ["253540","0503151"],
                        ["254115","0502606"],
                        ["254115","0502606"],
                        ["254227","0502503"],
                        ["254227","0502503"],
                        ["254908","0502201"],
                        ["254908","0502201"],
                        ["255301","0501807"],
                        ["255301","0501807"],
                        ["255709","0501735"],
                        ["255709","0501735"],
                        ["260450","0501611"],
                        ["260450","0501611"],
                        ["261018","0501852"],
                        ["261018","0501852"],
                        ["261515","0501907"],
                        ["261515","0501907"],
                        ["262217","0502026"],
                        ["262217","0502026"],
                        ["262424","0502218"],
                        ["262424","0502218"],
                        ["263148","0502315"],
                        ["263148","0502315"],
                        ["263420","0502759"]
                    ]
                },
                {
                    "min": 25,
                    "max": 79,
                    "points": [
                        ["265644","0500434"],
                        ["265234","0500855"],
                        ["265234","0500855"],
                        ["263420","0502759"],
                        ["263420","0502759"],
                        ["263148","0502315"],
                        ["263148","0502315"],
                        ["262424","0502218"],
                        ["262424","0502218"],
                        ["262217","0502026"],
                        ["262217","0502026"],
                        ["261515","0501907"],
                        ["261515","0501907"],
                        ["261018","0501852"],
                        ["261018","0501852"],
                        ["260412","0503022"],
                        ["260412","0503022"],
                        ["260448","0503158"],
                        ["260448","0503158"],
                        ["260456","0503229"],
                        ["260456","0503229"],
                        ["260508","0503323"],
                        ["260508","0503323"],
                        ["260510","0503340"],
                        ["260510","0503340"],
                        ["260517","0503525"],
                        ["260517","0503525"],
                        ["260816","0503525"],
                        ["260816","0503525"],
                        ["260807","0503741"],
                        ["260807","0503741"],
                        ["260738","0503953"],
                        ["260738","0503953"],
                        ["260651","0504158"],
                        ["260651","0504158"],
                        ["260547","0504354"],
                        ["260547","0504354"],
                        ["260428","0504537"],
                        ["260428","0504537"],
                        ["260255","0504705"],
                        ["260255","0504705"],
                        ["260111","0504816"],
                        ["260111","0504816"],
                        ["255918","0504908"],
                        ["255918","0504908"],
                        ["255719","0504940"],
                        ["255719","0504940"],
                        ["255517","0504951"],
                        ["255517","0504951"],
                        ["255316","0504940"],
                        ["255316","0504940"],
                        ["255117","0504908"],
                        ["255117","0504908"],
                        ["254924","0504816"],
                        ["254924","0504816"],
                        ["254458","0505205"],
                        ["254458","0505205"],
                        ["261706","0510440"],
                        ["261706","0510440"],
                        ["260838","0512245"],
                        ["260838","0512245"],
                        ["260908","0512320"],
                        ["260908","0512320"],
                        ["261523","0512353"],
                        ["261523","0512353"],
                        ["262134","0512301"],
                        ["262134","0512301"],
                        ["262744","0512142"],
                        ["262744","0512142"],
                        ["263333","0511902"],
                        ["263333","0511902"],
                        ["263855","0511522"],
                        ["263855","0511522"],
                        ["264342","0511050"],
                        ["264342","0511050"],
                        ["264747","0510531"],
                        ["264747","0510531"],
                        ["265105","0505933"],
                        ["265105","0505933"],
                        ["265330","0505305"],
                        ["265330","0505305"],
                        ["265458","0504617"],
                        ["265458","0504617"],
                        ["265553","0504134"],
                        ["265553","0504134"],
                        ["265644","0500434"]
                    ]
                },
                {
                    "min": 10,
                    "max": 24,
                    "points": [
                        ["263420","0502759"],
                        ["260816","0503525"],
                        ["260816","0503525"],
                        ["260807","0503741"],
                        ["260807","0503741"],
                        ["260738","0503953"],
                        ["260738","0503953"],
                        ["260651","0504158"],
                        ["260651","0504158"],
                        ["260547","0504354"],
                        ["260547","0504354"],
                        ["261706","0510440"],
                        ["261706","0510440"],
                        ["260838","0512245"],
                        ["260838","0512245"],
                        ["260908","0512320"],
                        ["260908","0512320"],
                        ["261523","0512353"],
                        ["261523","0512353"],
                        ["262134","0512301"],
                        ["262134","0512301"],
                        ["262744","0512142"],
                        ["262744","0512142"],
                        ["263333","0511902"],
                        ["263333","0511902"],
                        ["263855","0511522"],
                        ["263855","0511522"],
                        ["264342","0511050"],
                        ["264342","0511050"],
                        ["264747","0510531"],
                        ["264747","0510531"],
                        ["265105","0505933"],
                        ["265105","0505933"],
                        ["265330","0505305"],
                        ["265330","0505305"],
                        ["265458","0504617"],
                        ["265458","0504617"],
                        ["265553","0504134"],
                        ["265553","0504134"],
                        ["265644","0500434"],
                        ["265644","0500434"],
                        ["265234","0500855"],
                        ["265234","0500855"],
                        ["263420","0502759"]
                    ]
                },
                {
                    "min": 80,
                    "max": 169,
                    "points": [
                        ["251522","0503848"],
                        ["252849","0504455"],
                        ["253255","0504648"],
                        ["253433","0504737"],
                        ["253643","0504847"],
                        ["254227","0505109"],
                        ["254458","0505205"],
                        ["261706","0510440"],
                        ["260838","0512245"],
                        ["260908","0512320"],
                        ["261523","0512353"],
                        ["262134","0512301"],
                        ["262744","0512142"],
                        ["263333","0511902"],
                        ["263855","0511522"],
                        ["264342","0511050"],
                        ["264747","0510531"],
                        ["265105","0505933"],
                        ["265330","0505305"],
                        ["265458","0504617"],
                        ["265553","0504134"],
                        ["265644","0500434"],
                        ["265234","0500855"],
                        ["263420","0502759"],
                        ["263148","0502315"],
                        ["262424","0502218"],
                        ["262217","0502026"],
                        ["261515","0501907"],
                        ["261018","0501852"],
                        ["260450","0501611"],
                        ["255709","0501735"],
                        ["255301","0501807"],
                        ["254908","0502201"],
                        ["254227","0502503"],
                        ["254115","0502606"],
                        ["253540","0503151"],
                        ["253400","0503319"],
                        ["253111","0503544"],
                        ["252828","0503653"],
                        ["252510","0503716"],
                        ["252336","0503741"],
                        ["252144","0503818"],
                        ["251849","0503855"],
                        ["251522","0503848"]
                    ]
                }
            ]
        },
        {
            "id": "Sakhir",
            "group": "TWR",
            "owner": [
                "KHT",
                "BSA",
                "BA",
                "BBCL",
                "BBCH",
                "BB1"
            ],
            "sectors": [
                {
                    "min": 0,
                    "max": 24,
                    "points": [
                        ["255901","0502932"],
                        ["260446","0502857"],
                        ["260454","0502910"],
                        ["260511","0502941"],
                        ["260524","0503015"],
                        ["260532","0503051"],
                        ["260534","0503128"],
                        ["260532","0503204"],
                        ["260524","0503240"],
                        ["260511","0503314"],
                        ["260508","0503323"],
                        ["255923","0503358"],
                        ["255913","0503346"],
                        ["255856","0503314"],
                        ["255843","0503240"],
                        ["255835","0503204"],
                        ["255833","0503127"],
                        ["255835","0503050"],
                        ["255843","0503015"],
                        ["255901","0502932"]
                    ]
                }
            ]
        },
        {
            "id": "Isa",
            "group": "APP",
            "owner": [
                "BST",
                "BSA",
                "BA",
                "BBCL",
                "BBCH",
                "BB1"
            ],
            "sectors": [
                {
                    "min": 0,
                    "max": 79,
                    "points": [
                        ["255212","0502451"],
                        ["255051","0502155"],
                        ["254924","0502234"],
                        ["254740","0502345"],
                        ["254607","0502513"],
                        ["254448","0502657"],
                        ["254345","0502852"],
                        ["254258","0503058"],
                        ["254229","0503310"],
                        ["254220","0503525"],
                        ["254229","0503741"],
                        ["254258","0503953"],
                        ["254345","0504158"],
                        ["254448","0504354"],
                        ["254607","0504537"],
                        ["254740","0504705"],
                        ["254924","0504816"],
                        ["255117","0504908"],
                        ["255316","0504940"],
                        ["255517","0504951"],
                        ["255719","0504940"],
                        ["255918","0504908"],
                        ["260111","0504816"],
                        ["260255","0504705"],
                        ["260428","0504537"],
                        ["260547","0504354"],
                        ["260651","0504158"],
                        ["260738","0503953"],
                        ["260807","0503741"],
                        ["260816","0503525"],
                        ["260517","0503525"],
                        ["260510","0503340"],
                        ["260508","0503323"],
                        ["260456","0503229"],
                        ["260448","0503158"],
                        ["260412","0503023"],
                        ["260323","0502853"],
                        ["260300","0502817"],
                        ["260222","0502734"],
                        ["260110","0502625"],
                        ["255949","0502530"],
                        ["255823","0502451"],
                        ["255651","0502426"],
                        ["255517","0502418"],
                        ["255343","0502426"],
                        ["255212","0502451"]
                    ]
                }
            ]
        },
        {
            "id": "Bahrain",
            "group": "TWR",
            "owner": [
                "BT",
                "BA",
                "BBCL",
                "BBCH",
                "BB1"
            ],
            "sectors": [
                {
                    "min": 0,
                    "max": 24,
                    "points": [
                        ["262554","0503141"],
                        ["261459","0505022"],
                        ["260818","0504532"],
                        ["261224","0503803"],
                        ["261527","0503449"],
                        ["261527","0503248"],
                        ["261911","0502652"],
                        ["262554","0503141"]
                    ]
                }
            ]
        }
    ],
    "groups": {
        "CTR": {
            "name": "Bahrain",
            "colour": "#ce1126"
        },
        "APP": {
            "name": "Approach",
            "colour": "#0115b2"
        },
        "TWR": {
            "name": "Tower",
            "colour": "#ffffff"
        }
    },
    "positions": {
        "BB1": {
            "colours": [
                {
                    "hex": "#ce1126"
                }
            ],
            "callsign": "Bahrain Radar",
            "frequency": "127.525",
            "type": "CTR",
            "pre": [
                "OBBB"
            ]
        },
        "BB2": {
            "colours": [
                {
                    "hex": "#2663c0"
                }
            ],
            "callsign": "Bahrain Radar",
            "frequency": "132.125",
            "type": "CTR",
            "pre": [
                "OBBB"
            ]
        },
        "BB3": {
            "colours": [
                {
                    "hex": "#9832ff"
                }
            ],
            "callsign": "Bahrain Radar",
            "frequency": "127.575",
            "type": "CTR",
            "pre": [
                "OBBB"
            ]
        },
        "BBCH": {
            "colours": [
                {
                    "hex": "#d74051"
                }
            ],
            "callsign": "Bahrain Radar",
            "frequency": "124.300",
            "type": "CTR",
            "pre": [
                "OBBB"
            ]
        },
        "BBCL": {
            "colours": [
                {
                    "hex": "#a40d1e"
                }
            ],
            "callsign": "Bahrain Radar",
            "frequency": "122.300",
            "type": "CTR",
            "pre": [
                "OBBB"
            ]
        },
        "BBE": {
            "colours": [
                {
                    "hex": "#0F52ba"
                }
            ],
            "callsign": "Bahrain Radar",
            "frequency": "132.850",
            "type": "CTR",
            "pre": [
                "OBBB"
            ]
        },
        "BBN": {
            "colours": [
                {
                    "hex": "#7f00ff"
                }
            ],
            "callsign": "Bahrain Radar",
            "frequency": "126.700",
            "type": "CTR",
            "pre": [
                "OBBB"
            ]
        },
        "BA": {
            "colours": [
                {
                    "hex": "#0115b2"
                }
            ],
            "callsign": "Bahrain Approach",
            "frequency": "127.850",
            "type": "APP",
            "pre": [
                "OBBI"
            ]
        },
        "BT": {
            "callsign": "Bahrain Tower",
            "frequency": "118.500",
            "type": "TWR",
            "pre": [
                "OBBI"
            ]
        },
        "BSA": {
            "callsign": "Isa Radar",
            "frequency": "124.950",
            "type": "APP",
            "pre": [
                "OBBS"
            ]
        },
        "BST": {
            "callsign": "Isa Tower",
            "frequency": "125.450",
            "type": "TWR",
            "pre": [
                "OBBS"
            ]
        },
        "KHT": {
            "callsign": "Sakhir Tower",
            "frequency": "118.150",
            "type": "TWR",
            "pre": [
                "OBKH"
            ]
        }
    },
    "callsigns": {
        "DEL": {
            "": "Delivery",
            "P": "Planner"
        },
        "GND": {
            "": "Ground",
            "P": "Planner"
        },
        "TWR": {
            "": "Tower",
            "H": "Kopter",
            "I": "Information",
            "R": "Radio"
        },
        "APP": {
            "": "Approach"
        }
    },
    "airports": {
        "OBBI": {
            "callsign": "Bahrain",
            "coord": [
                26.270833,
                50.633611
            ],
            "topdown": [
                "BA",
                "BBCL",
                "BBCH",
                "BB1"
            ]
        },
        "OBBS": {
            "callsign": "Isa Airbase",
            "coord": [
                25.918364,
                50.5906
            ],
            "topdown": [
                "BSA",
                "BA",
                "BBCL",
                "BBCH",
                "BB1"
            ]
        },
        "OBKH": {
            "callsign": "Sakhir Airbase",
            "coord": [
                26.034722,
                50.524444
            ],
            "topdown": [
                "BSA",
                "BA",
                "BBCL",
                "BBCH",
                "BB1"
            ]
        }
    }
}
